gs2d/DefaultCommandHandler.py
gs2d/Driver.py
gs2d/Futaba.py
gs2d/ICommandHandler.py
gs2d/ISerialInterface.py
gs2d/RobotisP20.py
gs2d/SerialInterface.py
gs2d/Util.py
gs2d/__init__.py
gs2d-0.0.4.dist-info/LICENSE
gs2d-0.0.4.dist-info/METADATA
gs2d-0.0.4.dist-info/WHEEL
gs2d-0.0.4.dist-info/top_level.txt
gs2d-0.0.4.dist-info/RECORD
