Metadata-Version: 2.1
Name: gs2d
Version: 0.0.4
Summary: gs2d: The Library for Generic Serial-bus Servo Driver kr-sac001 for Python
Home-page: https://github.com/karakuri-products/gs2d-python
Author: Karakuri Products
Author-email: gs2d@krkrpro.com
License: Apache License Version 2.0
Platform: UNKNOWN
Requires-Dist: pyserial
